{
  "format": "line-sticker-phrase-set",
  "version": 1,
  "mode": "set",
  "name": "黑貓牧師·日常聊天",
  "phrases": [
    "早安",
    "晚安",
    "謝謝你",
    "好喔",
    "收到",
    "辛苦了",
    "對不起",
    "馬上到",
    "等你喔",
    "加油",
    "麻煩了",
    "讚喔",
    "真的假",
    "我懂了",
    "沒事",
    "笑死",
    "才不要",
    "太棒了",
    "抱歉啦",
    "拜啦",
    "來了",
    "好累",
    "開心",
    "委屈",
    "無語",
    "震驚",
    "期待",
    "害羞",
    "崩潰",
    "想你了",
    "等等啦",
    "好想你",
    "陪陪我",
    "不要嘛",
    "哼",
    "",
    "",
    "",
    "",
    ""
  ],
  "actionDescs": [
    "黑貓牧師穿著黑袍，戴著銀框眼鏡，雙手合十微微鞠躬，背景有柔和光圈，上方寫著黃色『早安』",
    "黑貓牧師手持蠟燭提燈，輕輕吹熄燭火，背景呈現深藍夜色，上方寫著紫色『晚安』",
    "黑貓牧師放下古老聖經，雙手捧在胸前，露出溫暖的微笑，上方寫著粉紅色『謝謝你』",
    "黑貓牧師點頭如搗蒜，紫聖帶隨之擺動，模樣乖巧，上方寫著綠色『好喔』",
    "黑貓牧師端正坐著，一隻手輕觸耳邊像在接聽，上方寫著橘色『收到』",
    "黑貓牧師溫柔地撫摸著一隻小花貓，眼神充滿慈愛，上方寫著咖啡色『辛苦了』",
    "黑貓牧師垂下耳朵，雙手抓著袖口，一臉愧疚的表情，上方寫著藍色『對不起』",
    "黑貓牧師拉起黑袍裙擺，邁開小碎步往前奔跑，上方寫著紅色『馬上到』",
    "黑貓牧師趴在桌邊，下巴靠在聖經上，眼神直勾勾地望著前方，上方寫著粉紅色『等你喔』",
    "黑貓牧師揮舞著鑲金邊的權杖，周圍飄散著星星特效，上方寫著黃色『加油』",
    "黑貓牧師恭敬地遞出一朵白色百合花，眼神真誠，上方寫著綠色『麻煩了』",
    "黑貓牧師豎起大拇指，眼睛瞇成彎月形，笑容燦爛，上方寫著橘色『讚喔』",
    "黑貓牧師拿下眼鏡擦拭，眼睛瞪大，嘴巴微張，上方寫著紫色『真的假』",
    "黑貓牧師嚴肅地點點頭，手放在胸口表示理解，上方寫著藍色『我懂了』",
    "黑貓牧師輕輕擺擺手，表情放鬆自然，背景有飄落的羽毛，上方寫著咖啡色『沒事』",
    "黑貓牧師笑到整隻貓倒在地上打滾，黑袍皺成一團，上方寫著紅色『笑死』",
    "黑貓牧師雙手交叉在胸前，別過頭去露出傲嬌表情，上方寫著粉紅色『才不要』",
    "黑貓牧師開心地跳起來，雙手高舉，周圍閃爍亮光，上方寫著黃色『太棒了』",
    "黑貓牧師拉著聖帶的尾端，低頭不好意思地抓抓臉，上方寫著綠色『抱歉啦』",
    "黑貓牧師優雅地揮動貓掌，向後退入陰影中，上方寫著紫色『拜啦』",
    "黑貓牧師從畫面邊緣探出頭，睜大水汪汪的眼睛，上方寫著橘色『來了』",
    "黑貓牧師軟綿綿地攤在軟墊上，眼睛半閉，看起來懶洋洋的，上方寫著藍色『好累』",
    "黑貓牧師在空中轉圈，身後拖曳著彩虹光軌，上方寫著紅色『開心』",
    "黑貓牧師眼角含淚，嘴唇微翹，看起來委屈巴巴的樣子，上方寫著咖啡色『委屈』",
    "黑貓牧師一臉呆滯，頭頂冒出三個問號，眼鏡滑到鼻尖，上方寫著紫色『無語』",
    "黑貓牧師驚訝得眼鏡掉落，雙手捧住臉頰，背景有震動特效，上方寫著紅色『震驚』",
    "黑貓牧師雙手貼在臉頰旁，眼睛發光地盯著前方看，上方寫著黃色『期待』",
    "黑貓牧師用黑袍遮住半邊臉，露出羞澀的眼神，臉頰泛紅，上方寫著粉紅色『害羞』",
    "黑貓牧師抱著聖經在地上抓狂，黑袍凌亂，看起來崩潰的模樣，上方寫著藍色『崩潰』",
    "黑貓牧師張開雙手，做出想擁抱的姿勢，表情十分渴望，上方寫著橘色『想你了』",
    "黑貓牧師拉住你的衣角，用力扯了兩下，表情懇求，上方寫著綠色『等等啦』",
    "黑貓牧師捧著蠟燭提燈，眼神深情地望著遠方，上方寫著粉紅色『好想你』",
    "黑貓牧師鑽進你的懷裡，蹭來蹭去撒嬌，表情非常滿足，上方寫著咖啡色『陪陪我』",
    "黑貓牧師撅起嘴巴，雙手握拳表示強烈抗議，上方寫著紅色『不要嘛』",
    "黑貓牧師鼓起腮幫子，雙手抱胸，氣呼呼地看向旁邊，上方寫著紫色『哼』",
    "【無字純動作】黑貓牧師閉眼祈禱，雙手交疊在聖經上，周圍圍繞著聖潔的光暈",
    "【無字純動作】黑貓牧師調整眼鏡，露出自信且溫柔的神情，背景有細小的星點",
    "【無字純動作】黑貓牧師用貓掌尖輕輕觸碰鏡頭，表情好奇又俏皮",
    "【無字純動作】黑貓牧師坐在蠟燭旁，靜靜地看著火苗搖曳，呈現沈思狀態",
    "【無字純動作】黑貓牧師舒服地捲成一團睡覺，尾巴環繞在身體周圍，畫面溫馨"
  ]
}
