{
  "format": "line-sticker-phrase-set",
  "version": 1,
  "mode": "set",
  "name": "期待制服妹·日常聊天",
  "phrases": [
    "早安",
    "晚安",
    "好喔",
    "謝謝",
    "收到",
    "真的假",
    "笑死",
    "對不起",
    "馬上到",
    "等你喔",
    "加油",
    "別鬧了",
    "才不要",
    "我懂了",
    "抱歉啦",
    "沒事",
    "太棒了",
    "我懂",
    "再說",
    "拜啦",
    "來了",
    "到了",
    "好累",
    "開心",
    "委屈",
    "無語",
    "震驚",
    "期待",
    "害羞",
    "崩潰",
    "想你了",
    "等等啦",
    "太扯",
    "算你狠",
    "煩欸",
    "",
    "",
    "",
    "",
    ""
  ],
  "actionDescs": [
    "期待制服妹雙手揮動，中分長髮隨動作飄逸，臉上掛著元氣笑容，上方寫著黃色『早安』",
    "期待制服妹穿著灰西裝外套，雙手合十放在臉頰旁睡覺，背景有幾顆小星星，上方寫著紫色『晚安』",
    "期待制服妹用力點頭，領帶隨動作晃動，比出大大的 OK 手勢，上方寫著青色『好喔』",
    "期待制服妹雙手奉上一個小禮物盒，眼神閃閃發光，臉部微紅，上方寫著粉紅色『謝謝』",
    "期待制服妹雙手敬禮，表情嚴肅認真，模樣帶點調皮感，上方寫著藍色『收到』",
    "期待制服妹瞪大雙眼，長髮稍微遮住一邊臉，張大嘴巴呈現驚訝狀，上方寫著橘色『真的假』",
    "期待制服妹笑到流淚，一隻手摀著肚子，另一隻手拍打桌面，上方寫著紅色『笑死』",
    "期待制服妹低著頭，拉著領帶的一角，表情懊惱又有點委屈，上方寫著咖啡色『對不起』",
    "期待制服妹穿著運動鞋背著包包，呈現奔跑姿勢，背景有速度線，上方寫著黃色『馬上到』",
    "期待制服妹趴在窗邊，手托著腮，眼神充滿期待地向外看，上方寫著紫色『等你喔』",
    "期待制服妹握緊雙拳，在胸前揮動加油，表情堅定又有精神，上方寫著青色『加油』",
    "期待制服妹單手推開螢幕，露出嫌棄的表情，長髮甩到一邊，上方寫著粉紅色『別鬧了』",
    "期待制服妹雙手交叉在胸前，把頭撇向一側，噘著嘴巴，上方寫著藍色『才不要』",
    "期待制服妹戴著眼鏡，指著筆記本，露出恍然大悟的表情，上方寫著橘色『我懂了』",
    "期待制服妹雙手合十請求，表情誠懇帶點狡黠，上方寫著咖啡色『抱歉啦』",
    "期待制服妹揮揮手，露出無所謂的微笑，表情輕鬆自然，上方寫著青色『沒事』",
    "期待制服妹雙手舉高比出愛心，背景有許多愛心特效，上方寫著粉紅色『太棒了』",
    "期待制服妹點頭如搗蒜，表情認同且眼神堅定，上方寫著紫色『我懂』",
    "期待制服妹把手放在耳朵後方，假裝沒聽到，露出戲謔的表情，上方寫著黃色『再說』",
    "期待制服妹背對鏡頭揮手，長髮飄逸，背景有夕陽感，上方寫著藍色『拜啦』",
    "期待制服妹探出頭來，從邊框下方露出狡黠的笑容，上方寫著橘色『來了』",
    "期待制服妹氣喘吁吁地扶著牆壁，領帶有點歪掉，上方寫著咖啡色『到了』",
    "期待制服妹整個人癱在椅子上，眼神空洞，頭髮凌亂，上方寫著紫色『好累』",
    "期待制服妹抱著一個大抱枕，在床上轉圈跳舞，表情極度快樂，上方寫著青色『開心』",
    "期待制服妹撇著嘴，眼眶泛紅，雙手拉著衣角，上方寫著藍色『委屈』",
    "期待制服妹面無表情，手裡拿著手機，眼神死地看著螢幕，上方寫著咖啡色『無語』",
    "期待制服妹下巴掉下來，眼睛變成驚嘆號，表情極度誇張，上方寫著紅色『震驚』",
    "期待制服妹握拳放在臉前，眼神充滿強烈的期待感，臉部發光，上方寫著黃色『期待』",
    "期待制服妹臉紅到耳根，遮住半邊臉，眼神害羞地偷看，上方寫著粉紅色『害羞』",
    "期待制服妹雙手抱頭，頭髮亂翹，表情崩潰扭曲，上方寫著橘色『崩潰』",
    "期待制服妹拿著手機，臉頰貼在手機上，露出甜甜的想念表情，上方寫著紫色『想你了』",
    "期待制服妹伸出一隻手掌阻擋，表情無奈地搖頭，上方寫著青色『等等啦』",
    "期待制服妹把眼鏡推到頭上，表情誇張地張大嘴巴，上方寫著紅色『太扯』",
    "期待制服妹露出邪惡的微笑，雙手交叉，眼神充滿戲謔，上方寫著藍色『算你狠』",
    "期待制服妹雙手揉太陽穴，表情煩躁，背景有雜亂線條，上方寫著咖啡色『煩欸』",
    "【無字純動作】期待制服妹在地上滾來滾去，中分長髮散開，表情呈現耍廢狀態",
    "【無字純動作】期待制服妹戴著耳機，閉著眼睛陶醉地聽音樂，身體左右搖擺",
    "【無字純動作】期待制服妹拿著鏡子整理領帶，表情極度專注，露出自信笑容",
    "【無字純動作】期待制服妹一臉狐疑地盯著前方，單眼微瞇，手指輕點下巴",
    "【無字純動作】期待制服妹猛地跳起來，雙手張開，表情充滿驚喜與興奮"
  ]
}
